oursin/__about__.py
oursin/__init__.py
oursin/camera.py
oursin/client.py
oursin/custom.py
oursin/dock.py
oursin/lines.py
oursin/meshes.py
oursin/particles.py
oursin/probes.py
oursin/renderer.py
oursin/text.py
oursin/texture.py
oursin/ui.py
oursin/utils.py
oursin/volumes.py
oursin/atlas/__init__.py
oursin/atlas/ontology.py
oursin/atlas/data/azba8.structures.json
oursin/atlas/data/bluebrain25.structures.json
oursin/atlas/data/cavefish2.structures.json
oursin/atlas/data/ccf100.structures.json
oursin/atlas/data/ccf25.structures.json
oursin/atlas/data/ccf50.structures.json
oursin/atlas/data/human500.structures.json
oursin/atlas/data/prairie_vole25.structures.json
oursin/atlas/data/princeton20.structures.json
oursin/atlas/data/waxholm39.structures.json
oursin/atlas/data/waxholm78.structures.json
oursin/colors/__init__.py
oursin/colors/colors.py
oursin/colors/xkcd_rgb.py
oursin-1.0.1.dist-info/METADATA
oursin-1.0.1.dist-info/WHEEL
oursin-1.0.1.dist-info/licenses/LICENSE
oursin-1.0.1.dist-info/RECORD
