Metadata-Version: 2.3
Name: oursin
Version: 1.0.1
Summary: Urchin - Universal Renderer Creating Helpful Images for Neuroscience Python API
Project-URL: Documentation, https://virtualbrainlab.org/urchin/installation_and_use.html
Project-URL: Issues, https://github.com/VirtualBrainLab/Urchin/issues
Project-URL: Source, https://github.com/VirtualBrainLab/Urchin
Author-email: Daniel Birman <daniel.birman@alleninstitute.org>
License: MIT
Keywords: neuroscience,renderer,virtualbrainlab
Classifier: Development Status :: 4 - Beta
Classifier: Intended Audience :: Science/Research
Classifier: Operating System :: OS Independent
Classifier: Programming Language :: Python
Classifier: Programming Language :: Python :: 3.8
Classifier: Programming Language :: Python :: 3.9
Classifier: Programming Language :: Python :: 3.10
Classifier: Programming Language :: Python :: 3.11
Classifier: Programming Language :: Python :: 3.12
Classifier: Programming Language :: Python :: Implementation :: CPython
Classifier: Programming Language :: Python :: Implementation :: PyPy
Requires-Python: <3.13,>=3.10
Requires-Dist: numpy>=1.23.3
Requires-Dist: pillow>=10.4.0
Requires-Dist: pydantic>=2.7.0
Requires-Dist: python-socketio[client]>=5.8
Requires-Dist: vbl-aquarium>=0.0.23
